jdic/__init__.py
jdic/jdic.py
jdic/settings.py
jdic/drivers/__init__.py
jdic/drivers/jsonpath_ng/__init__.py
jdic/drivers/mongo/__init__.py
jdic-1.0.3.dist-info/DESCRIPTION.rst
jdic-1.0.3.dist-info/METADATA
jdic-1.0.3.dist-info/RECORD
jdic-1.0.3.dist-info/WHEEL
jdic-1.0.3.dist-info/metadata.json
jdic-1.0.3.dist-info/top_level.txt
