Metadata-Version: 2.0
Name: jdic
Version: 1.0.3
Summary: A ready-to-use library which eases the manipulation of JSON-like documents, so that you can focus on logic instead of losing time in formal document manipulations.Jdic offers original features, but also embeds mission-critical 3rd party libraries and unite them all within a comprehensive easy-to-use API.
Home-page: https://github.com/kerfab/jdic
Author: Fabien Kerbouci
Author-email: UNKNOWN
License: UNKNOWN
Keywords: jdic json checksum diff patch find match mongo mongodb path
Platform: UNKNOWN
Classifier: Programming Language :: Python
Classifier: Development Status :: 5 - Production/Stable
Classifier: Programming Language :: Python :: 2
Classifier: Programming Language :: Python :: 3
Classifier: Programming Language :: Python :: Implementation :: CPython
Classifier: Topic :: Utilities
Requires-Dist: json-delta
Requires-Dist: json-schema
Requires-Dist: jsonpath-ng
Requires-Dist: mongoquery
